<?xml version="1.0" encoding="UTF-8"?>
<!--
Created with Funkin Packer v0.1.3 https://neeeoo.github.io/funkin-packer/
-->
<TextureAtlas imagePath="texture.png" width="8186" height="5801">
	<SubTexture name="lyrics0001" x="3413.5" y="2765.5" width="386" height="621" frameX="-95" frameY="-191" frameWidth="779.5" frameHeight="816"/>
	<SubTexture name="lyrics0002" x="3413.5" y="2765.5" width="386" height="621" frameX="-95" frameY="-191" frameWidth="779.5" frameHeight="816"/>
	<SubTexture name="lyrics0003" x="3413.5" y="2765.5" width="386" height="621" frameX="-95" frameY="-191" frameWidth="779.5" frameHeight="816"/>
	<SubTexture name="lyrics0004" x="3413.5" y="2765.5" width="386" height="621" frameX="-95" frameY="-191" frameWidth="779.5" frameHeight="816"/>
	<SubTexture name="lyrics0005" x="3413.5" y="2765.5" width="386" height="621" frameX="-95" frameY="-191" frameWidth="779.5" frameHeight="816"/>
	<SubTexture name="lyrics0006" x="3413.5" y="2765.5" width="386" height="621" frameX="-95" frameY="-191" frameWidth="779.5" frameHeight="816"/>
	<SubTexture name="lyrics0007" x="3413.5" y="2765.5" width="386" height="621" frameX="-95" frameY="-191" frameWidth="779.5" frameHeight="816"/>
	<SubTexture name="lyrics0008" x="7734.5" y="2882.5" width="380.5" height="621" frameX="-99.5" frameY="-191" frameWidth="779.5" frameHeight="816"/>
	<SubTexture name="lyrics0009" x="7734.5" y="2882.5" width="380.5" height="621" frameX="-99.5" frameY="-191" frameWidth="779.5" frameHeight="816"/>
	<SubTexture name="lyrics0010" x="3893.5" y="2162" width="367.5" height="615" frameX="-95.5" frameY="-196.5" frameWidth="779.5" frameHeight="816"/>
	<SubTexture name="lyrics0011" x="3893.5" y="2162" width="367.5" height="615" frameX="-95.5" frameY="-196.5" frameWidth="779.5" frameHeight="816"/>
	<SubTexture name="lyrics0012" x="4700" y="2175.5" width="445" height="609.5" frameX="-21.5" frameY="-202" frameWidth="779.5" frameHeight="816"/>
	<SubTexture name="lyrics0013" x="5146.5" y="2190.5" width="444.5" height="609.5" frameX="-22" frameY="-202" frameWidth="779.5" frameHeight="816"/>
	<SubTexture name="lyrics0014" x="4792.5" y="1579" width="462" height="595" frameX="-4.5" frameY="-216.5" frameWidth="779.5" frameHeight="816"/>
	<SubTexture name="lyrics0015" x="5256" y="1594" width="462" height="595" frameX="-4.5" frameY="-216.5" frameWidth="779.5" frameHeight="816"/>
	<SubTexture name="lyrics0016" x="2261" y="1547" width="468.5" height="594" frameX="-0" frameY="-217.5" frameWidth="779.5" frameHeight="816"/>
	<SubTexture name="lyrics0017" x="3297.5" y="1558" width="468.5" height="594" frameX="-0" frameY="-217.5" frameWidth="779.5" frameHeight="816"/>
	<SubTexture name="lyrics0018" x="2261" y="1547" width="468.5" height="594" frameX="-0" frameY="-217.5" frameWidth="779.5" frameHeight="816"/>
	<SubTexture name="lyrics0019" x="6230.5" y="1608.5" width="465" height="600.5" frameX="-3.5" frameY="-211" frameWidth="779.5" frameHeight="816"/>
	<SubTexture name="lyrics0020" x="7721" y="1667.5" width="464.5" height="600.5" frameX="-4" frameY="-211" frameWidth="779.5" frameHeight="816"/>
	<SubTexture name="lyrics0021" x="6230.5" y="1608.5" width="465" height="600.5" frameX="-3.5" frameY="-211" frameWidth="779.5" frameHeight="816"/>
	<SubTexture name="lyrics0022" x="3455.5" y="2162" width="436.5" height="602" frameX="-32" frameY="-209.5" frameWidth="779.5" frameHeight="816"/>
	<SubTexture name="lyrics0023" x="4262.5" y="2175" width="436" height="602" frameX="-32.5" frameY="-209.5" frameWidth="779.5" frameHeight="816"/>
	<SubTexture name="lyrics0024" x="2581.5" y="2142.5" width="435.5" height="601.5" frameX="-35" frameY="-210" frameWidth="779.5" frameHeight="816"/>
	<SubTexture name="lyrics0025" x="3018.5" y="2153.5" width="435.5" height="601.5" frameX="-35" frameY="-210" frameWidth="779.5" frameHeight="816"/>
	<SubTexture name="lyrics0026" x="6258.5" y="1033" width="448" height="574" frameX="-91.5" frameY="-238" frameWidth="779.5" frameHeight="816"/>
	<SubTexture name="lyrics0027" x="6258.5" y="1033" width="448" height="574" frameX="-91.5" frameY="-238" frameWidth="779.5" frameHeight="816"/>
	<SubTexture name="lyrics0028" x="6258.5" y="1033" width="448" height="574" frameX="-91.5" frameY="-238" frameWidth="779.5" frameHeight="816"/>
	<SubTexture name="lyrics0029" x="4674.5" y="1032.5" width="586" height="545" frameX="-74.5" frameY="-270" frameWidth="779.5" frameHeight="816"/>
	<SubTexture name="lyrics0030" x="4674.5" y="1032.5" width="586" height="545" frameX="-74.5" frameY="-270" frameWidth="779.5" frameHeight="816"/>
	<SubTexture name="lyrics0031" x="4674.5" y="1032.5" width="586" height="545" frameX="-74.5" frameY="-270" frameWidth="779.5" frameHeight="816"/>
	<SubTexture name="lyrics0032" x="1411.5" y="513.5" width="688" height="515" frameX="-72" frameY="-300" frameWidth="779.5" frameHeight="816"/>
	<SubTexture name="lyrics0033" x="1411.5" y="513.5" width="688" height="515" frameX="-72" frameY="-300" frameWidth="779.5" frameHeight="816"/>
	<SubTexture name="lyrics0034" x="1411.5" y="513.5" width="688" height="515" frameX="-72" frameY="-300" frameWidth="779.5" frameHeight="816"/>
	<SubTexture name="lyrics0035" x="1411.5" y="513.5" width="688" height="515" frameX="-72" frameY="-300" frameWidth="779.5" frameHeight="816"/>
	<SubTexture name="lyrics0036" x="1862" y="0.5" width="703.5" height="511.5" frameX="-70" frameY="-302.5" frameWidth="779.5" frameHeight="816"/>
	<SubTexture name="lyrics0037" x="1862" y="0.5" width="703.5" height="511.5" frameX="-70" frameY="-302.5" frameWidth="779.5" frameHeight="816"/>
	<SubTexture name="lyrics0038" x="2567" y="0.5" width="703.5" height="511.5" frameX="-70" frameY="-302.5" frameWidth="779.5" frameHeight="816"/>
	<SubTexture name="lyrics0039" x="3272" y="0.5" width="707.5" height="512.5" frameX="-70" frameY="-301" frameWidth="779.5" frameHeight="816"/>
	<SubTexture name="lyrics0040" x="3272" y="0.5" width="707.5" height="512.5" frameX="-70" frameY="-301" frameWidth="779.5" frameHeight="816"/>
	<SubTexture name="lyrics0041" x="3981" y="0.5" width="707.5" height="512.5" frameX="-70" frameY="-301" frameWidth="779.5" frameHeight="816"/>
	<SubTexture name="lyrics0042" x="2101" y="513.5" width="709.5" height="515" frameX="-70" frameY="-299" frameWidth="779.5" frameHeight="816"/>
	<SubTexture name="lyrics0043" x="2101" y="513.5" width="709.5" height="515" frameX="-70" frameY="-299" frameWidth="779.5" frameHeight="816"/>
	<SubTexture name="lyrics0044" x="2812" y="514.5" width="709.5" height="515" frameX="-70" frameY="-299" frameWidth="779.5" frameHeight="816"/>
	<SubTexture name="lyrics0045" x="2769" y="1031" width="709" height="516" frameX="-70" frameY="-298" frameWidth="779.5" frameHeight="816"/>
	<SubTexture name="lyrics0046" x="2769" y="1031" width="709" height="516" frameX="-70" frameY="-298" frameWidth="779.5" frameHeight="816"/>
	<SubTexture name="lyrics0047" x="3523" y="514.5" width="709" height="515.5" frameX="-70" frameY="-298.5" frameWidth="779.5" frameHeight="816"/>
	<SubTexture name="lyrics0048" x="4233.5" y="514.5" width="709" height="515.5" frameX="-70" frameY="-298.5" frameWidth="779.5" frameHeight="816"/>
	<SubTexture name="lyrics0049" x="4944" y="515.5" width="709" height="515.5" frameX="-70.5" frameY="-298.5" frameWidth="779.5" frameHeight="816"/>
	<SubTexture name="lyrics0050" x="5654.5" y="516" width="709" height="515.5" frameX="-70.5" frameY="-298.5" frameWidth="779.5" frameHeight="816"/>
	<SubTexture name="lyrics0051" x="4944" y="515.5" width="709" height="515.5" frameX="-70.5" frameY="-298.5" frameWidth="779.5" frameHeight="816"/>
	<SubTexture name="lyrics0052" x="6365" y="516" width="709" height="515.5" frameX="-70.5" frameY="-298.5" frameWidth="779.5" frameHeight="816"/>
	<SubTexture name="lyrics0053" x="637.5" y="991.5" width="709" height="515.5" frameX="-70.5" frameY="-298.5" frameWidth="779.5" frameHeight="816"/>
	<SubTexture name="lyrics0054" x="6365" y="516" width="709" height="515.5" frameX="-70.5" frameY="-298.5" frameWidth="779.5" frameHeight="816"/>
	<SubTexture name="lyrics0055" x="1348" y="1030" width="709" height="515.5" frameX="-70.5" frameY="-298.5" frameWidth="779.5" frameHeight="816"/>
	<SubTexture name="lyrics0056" x="2058.5" y="1030" width="709" height="515.5" frameX="-70.5" frameY="-298.5" frameWidth="779.5" frameHeight="816"/>
	<SubTexture name="lyrics0057" x="0.5" y="470" width="704" height="514.5" frameX="-70" frameY="-299.5" frameWidth="779.5" frameHeight="816"/>
	<SubTexture name="lyrics0058" x="0.5" y="470" width="704" height="514.5" frameX="-70" frameY="-299.5" frameWidth="779.5" frameHeight="816"/>
	<SubTexture name="lyrics0059" x="706" y="475.5" width="704" height="514.5" frameX="-70" frameY="-299.5" frameWidth="779.5" frameHeight="816"/>
	<SubTexture name="lyrics0060" x="0.5" y="470" width="704" height="514.5" frameX="-70" frameY="-299.5" frameWidth="779.5" frameHeight="816"/>
	<SubTexture name="lyrics0061" x="6296.5" y="0.5" width="703" height="514" frameX="-69.5" frameY="-300" frameWidth="779.5" frameHeight="816"/>
	<SubTexture name="lyrics0062" x="7001" y="0.5" width="703" height="514" frameX="-69.5" frameY="-300" frameWidth="779.5" frameHeight="816"/>
	<SubTexture name="lyrics0063" x="6296.5" y="0.5" width="703" height="514" frameX="-69.5" frameY="-300" frameWidth="779.5" frameHeight="816"/>
	<SubTexture name="lyrics0064" x="6296.5" y="0.5" width="703" height="514" frameX="-69.5" frameY="-300" frameWidth="779.5" frameHeight="816"/>
	<SubTexture name="lyrics0065" x="5608" y="0.5" width="687" height="513.5" frameX="-67" frameY="-300.5" frameWidth="779.5" frameHeight="816"/>
	<SubTexture name="lyrics0066" x="5608" y="0.5" width="687" height="513.5" frameX="-67" frameY="-300.5" frameWidth="779.5" frameHeight="816"/>
	<SubTexture name="lyrics0067" x="5608" y="0.5" width="687" height="513.5" frameX="-67" frameY="-300.5" frameWidth="779.5" frameHeight="816"/>
	<SubTexture name="lyrics0068" x="0.5" y="986" width="635.5" height="517.5" frameX="-76" frameY="-297.5" frameWidth="779.5" frameHeight="816"/>
	<SubTexture name="lyrics0069" x="0.5" y="986" width="635.5" height="517.5" frameX="-76" frameY="-297.5" frameWidth="779.5" frameHeight="816"/>
	<SubTexture name="lyrics0070" x="0.5" y="986" width="635.5" height="517.5" frameX="-76" frameY="-297.5" frameWidth="779.5" frameHeight="816"/>
	<SubTexture name="lyrics0071" x="7075.5" y="516" width="604" height="525" frameX="-75" frameY="-290" frameWidth="779.5" frameHeight="816"/>
	<SubTexture name="lyrics0072" x="7075.5" y="516" width="604" height="525" frameX="-75" frameY="-290" frameWidth="779.5" frameHeight="816"/>
	<SubTexture name="lyrics0073" x="7075.5" y="516" width="604" height="525" frameX="-75" frameY="-290" frameWidth="779.5" frameHeight="816"/>
	<SubTexture name="lyrics0074" x="7075.5" y="516" width="604" height="525" frameX="-75" frameY="-290" frameWidth="779.5" frameHeight="816"/>
	<SubTexture name="lyrics0075" x="3479.5" y="1031.5" width="602.5" height="525" frameX="-75" frameY="-290" frameWidth="779.5" frameHeight="816"/>
	<SubTexture name="lyrics0076" x="3479.5" y="1031.5" width="602.5" height="525" frameX="-75" frameY="-290" frameWidth="779.5" frameHeight="816"/>
	<SubTexture name="lyrics0077" x="3479.5" y="1031.5" width="602.5" height="525" frameX="-75" frameY="-290" frameWidth="779.5" frameHeight="816"/>
	<SubTexture name="lyrics0078" x="4083.5" y="1031.5" width="589.5" height="533" frameX="-83" frameY="-282" frameWidth="779.5" frameHeight="816"/>
	<SubTexture name="lyrics0079" x="4083.5" y="1031.5" width="589.5" height="533" frameX="-83" frameY="-282" frameWidth="779.5" frameHeight="816"/>
	<SubTexture name="lyrics0080" x="510.5" y="2093" width="492.5" height="598" frameX="-71" frameY="-212.5" frameWidth="779.5" frameHeight="816"/>
	<SubTexture name="lyrics0081" x="510.5" y="2093" width="492.5" height="598" frameX="-71" frameY="-212.5" frameWidth="779.5" frameHeight="816"/>
	<SubTexture name="lyrics0082" x="1004.5" y="2134" width="492.5" height="598" frameX="-71" frameY="-212.5" frameWidth="779.5" frameHeight="816"/>
	<SubTexture name="lyrics0083" x="5719.5" y="1603" width="509.5" height="595.5" frameX="-38.5" frameY="-216" frameWidth="779.5" frameHeight="816"/>
	<SubTexture name="lyrics0084" x="6697" y="1624.5" width="509.5" height="595.5" frameX="-38.5" frameY="-216" frameWidth="779.5" frameHeight="816"/>
	<SubTexture name="lyrics0085" x="3767.5" y="1566" width="511" height="594.5" frameX="-36.5" frameY="-217" frameWidth="779.5" frameHeight="816"/>
	<SubTexture name="lyrics0086" x="3767.5" y="1566" width="511" height="594.5" frameX="-36.5" frameY="-217" frameWidth="779.5" frameHeight="816"/>
	<SubTexture name="lyrics0087" x="3767.5" y="1566" width="511" height="594.5" frameX="-36.5" frameY="-217" frameWidth="779.5" frameHeight="816"/>
	<SubTexture name="lyrics0088" x="4280" y="1579" width="511" height="594.5" frameX="-36.5" frameY="-217" frameWidth="779.5" frameHeight="816"/>
	<SubTexture name="lyrics0089" x="4280" y="1579" width="511" height="594.5" frameX="-36.5" frameY="-217" frameWidth="779.5" frameHeight="816"/>
	<SubTexture name="lyrics0090" x="4280" y="1579" width="511" height="594.5" frameX="-36.5" frameY="-217" frameWidth="779.5" frameHeight="816"/>
	<SubTexture name="lyrics0091" x="7208" y="1667.5" width="511.5" height="595.5" frameX="-36" frameY="-216" frameWidth="779.5" frameHeight="816"/>
	<SubTexture name="lyrics0092" x="7208" y="1667.5" width="511.5" height="595.5" frameX="-36" frameY="-216" frameWidth="779.5" frameHeight="816"/>
	<SubTexture name="lyrics0093" x="7208" y="1667.5" width="511.5" height="595.5" frameX="-36" frameY="-216" frameWidth="779.5" frameHeight="816"/>
	<SubTexture name="lyrics0094" x="0.5" y="2088" width="508.5" height="596" frameX="-40" frameY="-215.5" frameWidth="779.5" frameHeight="816"/>
	<SubTexture name="lyrics0095" x="0.5" y="2088" width="508.5" height="596" frameX="-40" frameY="-215.5" frameWidth="779.5" frameHeight="816"/>
	<SubTexture name="lyrics0096" x="5770.5" y="2823.5" width="490" height="612.5" frameX="-63" frameY="-199" frameWidth="779.5" frameHeight="816"/>
	<SubTexture name="lyrics0097" x="5770.5" y="2823.5" width="490" height="612.5" frameX="-63" frameY="-199" frameWidth="779.5" frameHeight="816"/>
	<SubTexture name="lyrics0098" x="6262" y="2834.5" width="491.5" height="612.5" frameX="-60.5" frameY="-199" frameWidth="779.5" frameHeight="816"/>
	<SubTexture name="lyrics0099" x="6262" y="2834.5" width="491.5" height="612.5" frameX="-60.5" frameY="-199" frameWidth="779.5" frameHeight="816"/>
	<SubTexture name="lyrics0100" x="6755" y="2877.5" width="493.5" height="612.5" frameX="-58" frameY="-199" frameWidth="779.5" frameHeight="816"/>
	<SubTexture name="lyrics0101" x="6755" y="2877.5" width="493.5" height="612.5" frameX="-58" frameY="-199" frameWidth="779.5" frameHeight="816"/>
	<SubTexture name="lyrics0102" x="2452" y="3369.5" width="493.5" height="613.5" frameX="-58" frameY="-198" frameWidth="779.5" frameHeight="816"/>
	<SubTexture name="lyrics0103" x="1460" y="3357" width="494.5" height="613" frameX="-56.5" frameY="-198.5" frameWidth="779.5" frameHeight="816"/>
	<SubTexture name="lyrics0104" x="1460" y="3357" width="494.5" height="613" frameX="-56.5" frameY="-198.5" frameWidth="779.5" frameHeight="816"/>
	<SubTexture name="lyrics0105" x="1956" y="3358.5" width="494.5" height="613" frameX="-56.5" frameY="-198.5" frameWidth="779.5" frameHeight="816"/>
	<SubTexture name="lyrics0106" x="1956" y="3358.5" width="494.5" height="613" frameX="-56.5" frameY="-198.5" frameWidth="779.5" frameHeight="816"/>
	<SubTexture name="lyrics0107" x="4289" y="2786.5" width="494" height="612" frameX="-56.5" frameY="-199.5" frameWidth="779.5" frameHeight="816"/>
	<SubTexture name="lyrics0108" x="4289" y="2786.5" width="494" height="612" frameX="-56.5" frameY="-199.5" frameWidth="779.5" frameHeight="816"/>
	<SubTexture name="lyrics0109" x="4784.5" y="2801.5" width="494" height="612" frameX="-56.5" frameY="-199.5" frameWidth="779.5" frameHeight="816"/>
	<SubTexture name="lyrics0110" x="4784.5" y="2801.5" width="494" height="612" frameX="-56.5" frameY="-199.5" frameWidth="779.5" frameHeight="816"/>
	<SubTexture name="lyrics0111" x="5592.5" y="2200" width="489.5" height="611.5" frameX="-63" frameY="-200" frameWidth="779.5" frameHeight="816"/>
	<SubTexture name="lyrics0112" x="5592.5" y="2200" width="489.5" height="611.5" frameX="-63" frameY="-200" frameWidth="779.5" frameHeight="816"/>
	<SubTexture name="lyrics0113" x="6083.5" y="2210.5" width="489.5" height="611.5" frameX="-63" frameY="-200" frameWidth="779.5" frameHeight="816"/>
	<SubTexture name="lyrics0114" x="6083.5" y="2210.5" width="489.5" height="611.5" frameX="-63" frameY="-200" frameWidth="779.5" frameHeight="816"/>
	<SubTexture name="lyrics0115" x="6574.5" y="2221.5" width="488" height="611.5" frameX="-65.5" frameY="-200" frameWidth="779.5" frameHeight="816"/>
	<SubTexture name="lyrics0116" x="6574.5" y="2221.5" width="488" height="611.5" frameX="-65.5" frameY="-200" frameWidth="779.5" frameHeight="816"/>
	<SubTexture name="lyrics0117" x="7064" y="2264.5" width="488" height="611.5" frameX="-65.5" frameY="-200" frameWidth="779.5" frameHeight="816"/>
	<SubTexture name="lyrics0118" x="7064" y="2264.5" width="488" height="611.5" frameX="-65.5" frameY="-200" frameWidth="779.5" frameHeight="816"/>
	<SubTexture name="lyrics0119" x="7064" y="2264.5" width="488" height="611.5" frameX="-65.5" frameY="-200" frameWidth="779.5" frameHeight="816"/>
	<SubTexture name="lyrics0120" x="7553.5" y="2269.5" width="486.5" height="611.5" frameX="-68" frameY="-200" frameWidth="779.5" frameHeight="816"/>
	<SubTexture name="lyrics0121" x="7553.5" y="2269.5" width="486.5" height="611.5" frameX="-68" frameY="-200" frameWidth="779.5" frameHeight="816"/>
	<SubTexture name="lyrics0122" x="0.5" y="2685.5" width="486.5" height="611.5" frameX="-68" frameY="-200" frameWidth="779.5" frameHeight="816"/>
	<SubTexture name="lyrics0123" x="0.5" y="2685.5" width="486.5" height="611.5" frameX="-68" frameY="-200" frameWidth="779.5" frameHeight="816"/>
	<SubTexture name="lyrics0124" x="0.5" y="2685.5" width="486.5" height="611.5" frameX="-68" frameY="-200" frameWidth="779.5" frameHeight="816"/>
	<SubTexture name="lyrics0125" x="488.5" y="2692.5" width="485.5" height="611.5" frameX="-69" frameY="-200" frameWidth="779.5" frameHeight="816"/>
	<SubTexture name="lyrics0126" x="488.5" y="2692.5" width="485.5" height="611.5" frameX="-69" frameY="-200" frameWidth="779.5" frameHeight="816"/>
	<SubTexture name="lyrics0127" x="975.5" y="2733.5" width="485.5" height="611.5" frameX="-69" frameY="-200" frameWidth="779.5" frameHeight="816"/>
	<SubTexture name="lyrics0128" x="975.5" y="2733.5" width="485.5" height="611.5" frameX="-69" frameY="-200" frameWidth="779.5" frameHeight="816"/>
	<SubTexture name="lyrics0129" x="488.5" y="2692.5" width="485.5" height="611.5" frameX="-69" frameY="-200" frameWidth="779.5" frameHeight="816"/>
	<SubTexture name="lyrics0130" x="488.5" y="2692.5" width="485.5" height="611.5" frameX="-69" frameY="-200" frameWidth="779.5" frameHeight="816"/>
	<SubTexture name="lyrics0131" x="1462.5" y="2742.5" width="485.5" height="611.5" frameX="-69" frameY="-200" frameWidth="779.5" frameHeight="816"/>
	<SubTexture name="lyrics0132" x="1462.5" y="2742.5" width="485.5" height="611.5" frameX="-69" frameY="-200" frameWidth="779.5" frameHeight="816"/>
	<SubTexture name="lyrics0133" x="1949.5" y="2744" width="486.5" height="611.5" frameX="-68" frameY="-200" frameWidth="779.5" frameHeight="816"/>
	<SubTexture name="lyrics0134" x="1949.5" y="2744" width="486.5" height="611.5" frameX="-68" frameY="-200" frameWidth="779.5" frameHeight="816"/>
	<SubTexture name="lyrics0135" x="2437.5" y="2745.5" width="486.5" height="611.5" frameX="-68" frameY="-200" frameWidth="779.5" frameHeight="816"/>
	<SubTexture name="lyrics0136" x="2437.5" y="2745.5" width="486.5" height="611.5" frameX="-68" frameY="-200" frameWidth="779.5" frameHeight="816"/>
	<SubTexture name="lyrics0137" x="2925.5" y="2756.5" width="486.5" height="611.5" frameX="-68" frameY="-200" frameWidth="779.5" frameHeight="816"/>
	<SubTexture name="lyrics0138" x="2925.5" y="2756.5" width="486.5" height="611.5" frameX="-68" frameY="-200" frameWidth="779.5" frameHeight="816"/>
	<SubTexture name="lyrics0139" x="3801" y="2778.5" width="486.5" height="611.5" frameX="-68" frameY="-200" frameWidth="779.5" frameHeight="816"/>
	<SubTexture name="lyrics0140" x="5280" y="2813" width="489" height="612" frameX="-63.5" frameY="-199.5" frameWidth="779.5" frameHeight="816"/>
	<SubTexture name="lyrics0141" x="5280" y="2813" width="489" height="612" frameX="-63.5" frameY="-199.5" frameWidth="779.5" frameHeight="816"/>
	<SubTexture name="lyrics0142" x="5280" y="2813" width="489" height="612" frameX="-63.5" frameY="-199.5" frameWidth="779.5" frameHeight="816"/>
	<SubTexture name="lyrics0143" x="5280" y="2813" width="489" height="612" frameX="-63.5" frameY="-199.5" frameWidth="779.5" frameHeight="816"/>
	<SubTexture name="lyrics0144" x="7250" y="2882.5" width="483" height="612.5" frameX="-71" frameY="-199" frameWidth="779.5" frameHeight="816"/>
	<SubTexture name="lyrics0145" x="7250" y="2882.5" width="483" height="612.5" frameX="-71" frameY="-199" frameWidth="779.5" frameHeight="816"/>
	<SubTexture name="lyrics0146" x="7250" y="2882.5" width="483" height="612.5" frameX="-71" frameY="-199" frameWidth="779.5" frameHeight="816"/>
	<SubTexture name="lyrics0147" x="5262" y="1033" width="478" height="559.5" frameX="-77.5" frameY="-252" frameWidth="779.5" frameHeight="816"/>
	<SubTexture name="lyrics0148" x="5262" y="1033" width="478" height="559.5" frameX="-77.5" frameY="-252" frameWidth="779.5" frameHeight="816"/>
	<SubTexture name="lyrics0149" x="1414" y="0.5" width="446.5" height="476" frameX="-126" frameY="-337.5" frameWidth="779.5" frameHeight="816"/>
	<SubTexture name="lyrics0150" x="1414" y="0.5" width="446.5" height="476" frameX="-126" frameY="-337.5" frameWidth="779.5" frameHeight="816"/>
	<SubTexture name="lyrics0151" x="473" y="0.5" width="467.5" height="468" frameX="-127" frameY="-345.5" frameWidth="779.5" frameHeight="816"/>
	<SubTexture name="lyrics0152" x="473" y="0.5" width="467.5" height="468" frameX="-127" frameY="-345.5" frameWidth="779.5" frameHeight="816"/>
	<SubTexture name="lyrics0153" x="0.5" y="0.5" width="471" height="466.5" frameX="-127.5" frameY="-347" frameWidth="779.5" frameHeight="816"/>
	<SubTexture name="lyrics0154" x="0.5" y="0.5" width="471" height="466.5" frameX="-127.5" frameY="-347" frameWidth="779.5" frameHeight="816"/>
	<SubTexture name="lyrics0155" x="0.5" y="0.5" width="471" height="466.5" frameX="-127.5" frameY="-347" frameWidth="779.5" frameHeight="816"/>
	<SubTexture name="lyrics0156" x="942" y="0.5" width="470.5" height="473.5" frameX="-128" frameY="-340" frameWidth="779.5" frameHeight="816"/>
	<SubTexture name="lyrics0157" x="942" y="0.5" width="470.5" height="473.5" frameX="-128" frameY="-340" frameWidth="779.5" frameHeight="816"/>
	<SubTexture name="lyrics0158" x="942" y="0.5" width="470.5" height="473.5" frameX="-128" frameY="-340" frameWidth="779.5" frameHeight="816"/>
	<SubTexture name="lyrics0159" x="4690" y="0.5" width="457.5" height="512.5" frameX="-127.5" frameY="-301" frameWidth="779.5" frameHeight="816"/>
	<SubTexture name="lyrics0160" x="5149" y="0.5" width="457.5" height="512.5" frameX="-127.5" frameY="-301" frameWidth="779.5" frameHeight="816"/>
	<SubTexture name="lyrics0161" x="5149" y="0.5" width="457.5" height="512.5" frameX="-127.5" frameY="-301" frameWidth="779.5" frameHeight="816"/>
	<SubTexture name="lyrics0162" x="4346" y="3400" width="370" height="634.5" frameX="-125" frameY="-179.5" frameWidth="779.5" frameHeight="816"/>
	<SubTexture name="lyrics0163" x="4346" y="3400" width="370" height="634.5" frameX="-125" frameY="-179.5" frameWidth="779.5" frameHeight="816"/>
	<SubTexture name="lyrics0164" x="3396.5" y="4012" width="355.5" height="793.5" frameX="-107.5" frameY="-22" frameWidth="779.5" frameHeight="816"/>
	<SubTexture name="lyrics0165" x="3396.5" y="4012" width="355.5" height="793.5" frameX="-107.5" frameY="-22" frameWidth="779.5" frameHeight="816"/>
	<SubTexture name="lyrics0166" x="3753.5" y="4025.5" width="355.5" height="793.5" frameX="-107.5" frameY="-22" frameWidth="779.5" frameHeight="816"/>
	<SubTexture name="lyrics0167" x="6331.5" y="4152.5" width="362.5" height="810.5" frameX="-94.5" frameY="-5" frameWidth="779.5" frameHeight="816"/>
	<SubTexture name="lyrics0168" x="6695.5" y="4161.5" width="362.5" height="810.5" frameX="-94.5" frameY="-5" frameWidth="779.5" frameHeight="816"/>
	<SubTexture name="lyrics0169" x="7059.5" y="4162" width="362.5" height="810.5" frameX="-94.5" frameY="-5" frameWidth="779.5" frameHeight="816"/>
	<SubTexture name="lyrics0170" x="374.5" y="4599.5" width="365" height="813.5" frameX="-91.5" frameY="-2" frameWidth="779.5" frameHeight="816"/>
	<SubTexture name="lyrics0171" x="374.5" y="4599.5" width="365" height="813.5" frameX="-91.5" frameY="-2" frameWidth="779.5" frameHeight="816"/>
	<SubTexture name="lyrics0172" x="741" y="4657" width="365" height="813.5" frameX="-91.5" frameY="-2" frameWidth="779.5" frameHeight="816"/>
	<SubTexture name="lyrics0173" x="3351.5" y="4807" width="367.5" height="815.5" frameX="-88.5" frameY="-0" frameWidth="779.5" frameHeight="816"/>
	<SubTexture name="lyrics0174" x="3720.5" y="4820.5" width="367.5" height="815.5" frameX="-88.5" frameY="-0" frameWidth="779.5" frameHeight="816"/>
	<SubTexture name="lyrics0175" x="4089.5" y="4835" width="367.5" height="815.5" frameX="-88.5" frameY="-0" frameWidth="779.5" frameHeight="816"/>
	<SubTexture name="lyrics0176" x="4458.5" y="4846.5" width="369" height="815.5" frameX="-87" frameY="-0" frameWidth="779.5" frameHeight="816"/>
	<SubTexture name="lyrics0177" x="4458.5" y="4846.5" width="369" height="815.5" frameX="-87" frameY="-0" frameWidth="779.5" frameHeight="816"/>
	<SubTexture name="lyrics0178" x="4829" y="4864" width="369" height="815.5" frameX="-87" frameY="-0" frameWidth="779.5" frameHeight="816"/>
	<SubTexture name="lyrics0179" x="5199.5" y="4870.5" width="369" height="815.5" frameX="-87" frameY="-0" frameWidth="779.5" frameHeight="816"/>
	<SubTexture name="lyrics0180" x="5570" y="4885.5" width="370" height="815.5" frameX="-85.5" frameY="-0" frameWidth="779.5" frameHeight="816"/>
	<SubTexture name="lyrics0181" x="5941.5" y="4915.5" width="370" height="815.5" frameX="-85.5" frameY="-0" frameWidth="779.5" frameHeight="816"/>
	<SubTexture name="lyrics0182" x="6313" y="4964.5" width="370" height="815.5" frameX="-85.5" frameY="-0" frameWidth="779.5" frameHeight="816"/>
	<SubTexture name="lyrics0183" x="6313" y="4964.5" width="370" height="815.5" frameX="-85.5" frameY="-0" frameWidth="779.5" frameHeight="816"/>
	<SubTexture name="lyrics0184" x="6684.5" y="4973.5" width="370" height="815.5" frameX="-85.5" frameY="-0" frameWidth="779.5" frameHeight="816"/>
	<SubTexture name="lyrics0185" x="7056" y="4985" width="370" height="815.5" frameX="-85.5" frameY="-0" frameWidth="779.5" frameHeight="816"/>
	<SubTexture name="lyrics0186" x="7427.5" y="4985" width="370" height="815.5" frameX="-85.5" frameY="-0" frameWidth="779.5" frameHeight="816"/>
	<SubTexture name="lyrics0187" x="7799" y="4985" width="370" height="815.5" frameX="-85.5" frameY="-0" frameWidth="779.5" frameHeight="816"/>
	<SubTexture name="lyrics0188" x="1107.5" y="4690.5" width="372.5" height="814.5" frameX="-83" frameY="-1" frameWidth="779.5" frameHeight="816"/>
	<SubTexture name="lyrics0189" x="1107.5" y="4690.5" width="372.5" height="814.5" frameX="-83" frameY="-1" frameWidth="779.5" frameHeight="816"/>
	<SubTexture name="lyrics0190" x="1481.5" y="4724" width="372.5" height="814.5" frameX="-83" frameY="-1" frameWidth="779.5" frameHeight="816"/>
	<SubTexture name="lyrics0191" x="1855.5" y="4725.5" width="372.5" height="814.5" frameX="-83" frameY="-1" frameWidth="779.5" frameHeight="816"/>
	<SubTexture name="lyrics0192" x="2229.5" y="4774" width="372.5" height="814.5" frameX="-83" frameY="-1" frameWidth="779.5" frameHeight="816"/>
	<SubTexture name="lyrics0193" x="2603.5" y="4789" width="372.5" height="814.5" frameX="-83" frameY="-1" frameWidth="779.5" frameHeight="816"/>
	<SubTexture name="lyrics0194" x="2977.5" y="4802.5" width="372.5" height="814.5" frameX="-83" frameY="-1" frameWidth="779.5" frameHeight="816"/>
	<SubTexture name="lyrics0195" x="2977.5" y="4802.5" width="372.5" height="814.5" frameX="-83" frameY="-1" frameWidth="779.5" frameHeight="816"/>
	<SubTexture name="lyrics0196" x="7423.5" y="4171.5" width="372.5" height="812" frameX="-83" frameY="-3.5" frameWidth="779.5" frameHeight="816"/>
	<SubTexture name="lyrics0197" x="7797.5" y="4171.5" width="372.5" height="812" frameX="-83" frameY="-3.5" frameWidth="779.5" frameHeight="816"/>
	<SubTexture name="lyrics0198" x="0.5" y="4599.5" width="372.5" height="812" frameX="-83" frameY="-3.5" frameWidth="779.5" frameHeight="816"/>
	<SubTexture name="lyrics0199" x="5582.5" y="4076.5" width="373" height="807.5" frameX="-82.5" frameY="-8" frameWidth="779.5" frameHeight="816"/>
	<SubTexture name="lyrics0200" x="5957" y="4106.5" width="373" height="807.5" frameX="-82.5" frameY="-8" frameWidth="779.5" frameHeight="816"/>
	<SubTexture name="lyrics0201" x="5210" y="4065" width="371" height="804" frameX="-84.5" frameY="-12" frameWidth="779.5" frameHeight="816"/>
	<SubTexture name="lyrics0202" x="5210" y="4065" width="371" height="804" frameX="-84.5" frameY="-12" frameWidth="779.5" frameHeight="816"/>
	<SubTexture name="lyrics0203" x="4110.5" y="4036" width="365" height="797.5" frameX="-91" frameY="-18.5" frameWidth="779.5" frameHeight="816"/>
	<SubTexture name="lyrics0204" x="4477" y="4047.5" width="365" height="797.5" frameX="-91" frameY="-18.5" frameWidth="779.5" frameHeight="816"/>
	<SubTexture name="lyrics0205" x="4843.5" y="4065" width="365" height="797.5" frameX="-91" frameY="-18.5" frameWidth="779.5" frameHeight="816"/>
	<SubTexture name="lyrics0206" x="3033.5" y="4012" width="361.5" height="789" frameX="-95" frameY="-27" frameWidth="779.5" frameHeight="816"/>
	<SubTexture name="lyrics0207" x="2308.5" y="3984.5" width="361" height="788" frameX="-95.5" frameY="-28" frameWidth="779.5" frameHeight="816"/>
	<SubTexture name="lyrics0208" x="2671" y="3999.5" width="361" height="788" frameX="-95.5" frameY="-28" frameWidth="779.5" frameHeight="816"/>
	<SubTexture name="lyrics0209" x="1559.5" y="3971.5" width="373" height="751" frameX="-86.5" frameY="-65" frameWidth="779.5" frameHeight="816"/>
	<SubTexture name="lyrics0210" x="1934" y="3973" width="373" height="751" frameX="-86.5" frameY="-65" frameWidth="779.5" frameHeight="816"/>
	<SubTexture name="lyrics0211" x="1934" y="3973" width="373" height="751" frameX="-86.5" frameY="-65" frameWidth="779.5" frameHeight="816"/>
	<SubTexture name="lyrics0212" x="1159" y="3971.5" width="399" height="717.5" frameX="-56" frameY="-98" frameWidth="779.5" frameHeight="816"/>
	<SubTexture name="lyrics0213" x="1159" y="3971.5" width="399" height="717.5" frameX="-56" frameY="-98" frameWidth="779.5" frameHeight="816"/>
	<SubTexture name="lyrics0214" x="1159" y="3971.5" width="399" height="717.5" frameX="-56" frameY="-98" frameWidth="779.5" frameHeight="816"/>
	<SubTexture name="lyrics0215" x="755.5" y="3967" width="402" height="688.5" frameX="-51.5" frameY="-124.5" frameWidth="779.5" frameHeight="816"/>
	<SubTexture name="lyrics0216" x="755.5" y="3967" width="402" height="688.5" frameX="-51.5" frameY="-124.5" frameWidth="779.5" frameHeight="816"/>
	<SubTexture name="lyrics0217" x="366" y="3924.5" width="388" height="673.5" frameX="-68.5" frameY="-140" frameWidth="779.5" frameHeight="816"/>
	<SubTexture name="lyrics0218" x="366" y="3924.5" width="388" height="673.5" frameX="-68.5" frameY="-140" frameWidth="779.5" frameHeight="816"/>
	<SubTexture name="lyrics0219" x="7620" y="3505" width="374.5" height="665" frameX="-83" frameY="-148.5" frameWidth="779.5" frameHeight="816"/>
	<SubTexture name="lyrics0220" x="7620" y="3505" width="374.5" height="665" frameX="-83" frameY="-148.5" frameWidth="779.5" frameHeight="816"/>
	<SubTexture name="lyrics0221" x="7250" y="3496.5" width="368.5" height="664" frameX="-90" frameY="-149.5" frameWidth="779.5" frameHeight="816"/>
	<SubTexture name="lyrics0222" x="6522.5" y="3491.5" width="363.5" height="659.5" frameX="-96" frameY="-154" frameWidth="779.5" frameHeight="816"/>
	<SubTexture name="lyrics0223" x="6522.5" y="3491.5" width="363.5" height="659.5" frameX="-96" frameY="-154" frameWidth="779.5" frameHeight="816"/>
	<SubTexture name="lyrics0224" x="6162" y="3448.5" width="359" height="656.5" frameX="-102" frameY="-157" frameWidth="779.5" frameHeight="816"/>
	<SubTexture name="lyrics0225" x="6162" y="3448.5" width="359" height="656.5" frameX="-102" frameY="-157" frameWidth="779.5" frameHeight="816"/>
	<SubTexture name="lyrics0226" x="6887.5" y="3491.5" width="361" height="668.5" frameX="-103.5" frameY="-145" frameWidth="779.5" frameHeight="816"/>
	<SubTexture name="lyrics0227" x="6887.5" y="3491.5" width="361" height="668.5" frameX="-103.5" frameY="-145" frameWidth="779.5" frameHeight="816"/>
	<SubTexture name="lyrics0228" x="0.5" y="3918.5" width="364" height="670" frameX="-105.5" frameY="-143.5" frameWidth="779.5" frameHeight="816"/>
	<SubTexture name="lyrics0229" x="0.5" y="3918.5" width="364" height="670" frameX="-105.5" frameY="-143.5" frameWidth="779.5" frameHeight="816"/>
	<SubTexture name="lyrics0230" x="2947" y="3369.5" width="426.5" height="628.5" frameX="-105.5" frameY="-185" frameWidth="779.5" frameHeight="816"/>
	<SubTexture name="lyrics0231" x="2947" y="3369.5" width="426.5" height="628.5" frameX="-105.5" frameY="-185" frameWidth="779.5" frameHeight="816"/>
	<SubTexture name="lyrics0232" x="612.5" y="1508.5" width="610.5" height="583" frameX="-98.5" frameY="-231" frameWidth="779.5" frameHeight="816"/>
	<SubTexture name="lyrics0233" x="612.5" y="1508.5" width="610.5" height="583" frameX="-98.5" frameY="-231" frameWidth="779.5" frameHeight="816"/>
	<SubTexture name="lyrics0234" x="612.5" y="1508.5" width="610.5" height="583" frameX="-98.5" frameY="-231" frameWidth="779.5" frameHeight="816"/>
	<SubTexture name="lyrics0235" x="612.5" y="1508.5" width="610.5" height="583" frameX="-98.5" frameY="-231" frameWidth="779.5" frameHeight="816"/>
	<SubTexture name="lyrics0236" x="0.5" y="1505" width="610.5" height="581.5" frameX="-101" frameY="-232.5" frameWidth="779.5" frameHeight="816"/>
	<SubTexture name="lyrics0237" x="0.5" y="1505" width="610.5" height="581.5" frameX="-101" frameY="-232.5" frameWidth="779.5" frameHeight="816"/>
	<SubTexture name="lyrics0238" x="6708" y="1042.5" width="617.5" height="580.5" frameX="-101" frameY="-233.5" frameWidth="779.5" frameHeight="816"/>
	<SubTexture name="lyrics0239" x="7327" y="1085.5" width="617.5" height="580.5" frameX="-101" frameY="-233.5" frameWidth="779.5" frameHeight="816"/>
	<SubTexture name="lyrics0240" x="7327" y="1085.5" width="617.5" height="580.5" frameX="-101" frameY="-233.5" frameWidth="779.5" frameHeight="816"/>
	<SubTexture name="lyrics0241" x="1695" y="1547" width="564.5" height="592.5" frameX="-99" frameY="-221.5" frameWidth="779.5" frameHeight="816"/>
	<SubTexture name="lyrics0242" x="1695" y="1547" width="564.5" height="592.5" frameX="-99" frameY="-221.5" frameWidth="779.5" frameHeight="816"/>
	<SubTexture name="lyrics0243" x="2731" y="1548.5" width="565" height="592.5" frameX="-98.5" frameY="-221.5" frameWidth="779.5" frameHeight="816"/>
	<SubTexture name="lyrics0244" x="1498.5" y="2141" width="540" height="600" frameX="-98.5" frameY="-214" frameWidth="779.5" frameHeight="816"/>
	<SubTexture name="lyrics0245" x="2040" y="2142.5" width="540" height="600" frameX="-98.5" frameY="-214" frameWidth="779.5" frameHeight="816"/>
	<SubTexture name="lyrics0246" x="7705.5" y="0.5" width="468" height="536.5" frameX="-62.5" frameY="-277.5" frameWidth="779.5" frameHeight="816"/>
	<SubTexture name="lyrics0247" x="7705.5" y="0.5" width="468" height="536.5" frameX="-62.5" frameY="-277.5" frameWidth="779.5" frameHeight="816"/>
	<SubTexture name="lyrics0248" x="7705.5" y="0.5" width="468" height="536.5" frameX="-62.5" frameY="-277.5" frameWidth="779.5" frameHeight="816"/>
	<SubTexture name="lyrics0249" x="7681" y="538.5" width="460" height="545.5" frameX="-69" frameY="-268.5" frameWidth="779.5" frameHeight="816"/>
	<SubTexture name="lyrics0250" x="7681" y="538.5" width="460" height="545.5" frameX="-69" frameY="-268.5" frameWidth="779.5" frameHeight="816"/>
	<SubTexture name="lyrics0251" x="5741.5" y="1033" width="515.5" height="568.5" frameX="-13" frameY="-245" frameWidth="779.5" frameHeight="816"/>
	<SubTexture name="lyrics0252" x="5741.5" y="1033" width="515.5" height="568.5" frameX="-13" frameY="-245" frameWidth="779.5" frameHeight="816"/>
	<SubTexture name="lyrics0253" x="1224.5" y="1547" width="469" height="585.5" frameX="-58" frameY="-228" frameWidth="779.5" frameHeight="816"/>
	<SubTexture name="lyrics0254" x="1224.5" y="1547" width="469" height="585.5" frameX="-58" frameY="-228" frameWidth="779.5" frameHeight="816"/>
	<SubTexture name="lyrics0255" x="4717.5" y="3415" width="482.5" height="631" frameX="-55.5" frameY="-177" frameWidth="779.5" frameHeight="816"/>
	<SubTexture name="lyrics0256" x="4717.5" y="3415" width="482.5" height="631" frameX="-55.5" frameY="-177" frameWidth="779.5" frameHeight="816"/>
	<SubTexture name="lyrics0257" x="5681" y="3437.5" width="479.5" height="637.5" frameX="-56" frameY="-173" frameWidth="779.5" frameHeight="816"/>
	<SubTexture name="lyrics0258" x="5201.5" y="3426.5" width="478" height="637" frameX="-56.5" frameY="-173" frameWidth="779.5" frameHeight="816"/>
	<SubTexture name="lyrics0259" x="3860.5" y="3400" width="484" height="624" frameX="-50.5" frameY="-186" frameWidth="779.5" frameHeight="816"/>
	<SubTexture name="lyrics0260" x="3860.5" y="3400" width="484" height="624" frameX="-50.5" frameY="-186" frameWidth="779.5" frameHeight="816"/>
	<SubTexture name="lyrics0261" x="486" y="3305.5" width="487" height="617.5" frameX="-48" frameY="-192" frameWidth="779.5" frameHeight="816"/>
	<SubTexture name="lyrics0262" x="486" y="3305.5" width="487" height="617.5" frameX="-48" frameY="-192" frameWidth="779.5" frameHeight="816"/>
	<SubTexture name="lyrics0263" x="486" y="3305.5" width="487" height="617.5" frameX="-48" frameY="-192" frameWidth="779.5" frameHeight="816"/>
	<SubTexture name="lyrics0264" x="0.5" y="3298.5" width="484" height="618.5" frameX="-51" frameY="-191" frameWidth="779.5" frameHeight="816"/>
	<SubTexture name="lyrics0265" x="0.5" y="3298.5" width="484" height="618.5" frameX="-51" frameY="-191" frameWidth="779.5" frameHeight="816"/>
	<SubTexture name="lyrics0266" x="0.5" y="3298.5" width="484" height="618.5" frameX="-51" frameY="-191" frameWidth="779.5" frameHeight="816"/>
	<SubTexture name="lyrics0267" x="974.5" y="3346.5" width="484" height="619" frameX="-51" frameY="-190.5" frameWidth="779.5" frameHeight="816"/>
	<SubTexture name="lyrics0268" x="974.5" y="3346.5" width="484" height="619" frameX="-51" frameY="-190.5" frameWidth="779.5" frameHeight="816"/>
	<SubTexture name="lyrics0269" x="3375" y="3391.5" width="484" height="619" frameX="-51" frameY="-190.5" frameWidth="779.5" frameHeight="816"/>
	<SubTexture name="lyrics0270" x="3375" y="3391.5" width="484" height="619" frameX="-51" frameY="-190.5" frameWidth="779.5" frameHeight="816"/>
	<SubTexture name="lyrics0271" x="3375" y="3391.5" width="484" height="619" frameX="-51" frameY="-190.5" frameWidth="779.5" frameHeight="816"/>
	<SubTexture name="lyrics0272" x="3375" y="3391.5" width="484" height="619" frameX="-51" frameY="-190.5" frameWidth="779.5" frameHeight="816"/>
	<SubTexture name="lyrics0273" x="3375" y="3391.5" width="484" height="619" frameX="-51" frameY="-190.5" frameWidth="779.5" frameHeight="816"/>
	<SubTexture name="lyrics0274" x="3375" y="3391.5" width="484" height="619" frameX="-51" frameY="-190.5" frameWidth="779.5" frameHeight="816"/>
	<SubTexture name="lyrics0275" x="3375" y="3391.5" width="484" height="619" frameX="-51" frameY="-190.5" frameWidth="779.5" frameHeight="816"/>
	<SubTexture name="lyrics0276" x="3375" y="3391.5" width="484" height="619" frameX="-51" frameY="-190.5" frameWidth="779.5" frameHeight="816"/>
	<SubTexture name="lyrics0277" x="3375" y="3391.5" width="484" height="619" frameX="-51" frameY="-190.5" frameWidth="779.5" frameHeight="816"/>
</TextureAtlas>